pyplaylib/pyplaylib.py
pyplaylib-0.0.1.dist-info/DESCRIPTION.rst
pyplaylib-0.0.1.dist-info/METADATA
pyplaylib-0.0.1.dist-info/RECORD
pyplaylib-0.0.1.dist-info/WHEEL
pyplaylib-0.0.1.dist-info/metadata.json
pyplaylib-0.0.1.dist-info/top_level.txt
