Metadata-Version: 2.0
Name: pyplaylib
Version: 0.0.1
Summary: pyplay
Home-page: https://github.com/uperpython/pyplaylib
Author: Yaya Souno Qurashi
Author-email: umarmoiz2010@gmail.com
License: Apache2
Platform: UNKNOWN
